datastore_to_gcs/__init__.py
datastore_to_gcs/cloud_storage.py
datastore_to_gcs/util.py
datastore_to_gcs-0.3.dist-info/DESCRIPTION.rst
datastore_to_gcs-0.3.dist-info/METADATA
datastore_to_gcs-0.3.dist-info/RECORD
datastore_to_gcs-0.3.dist-info/WHEEL
datastore_to_gcs-0.3.dist-info/metadata.json
datastore_to_gcs-0.3.dist-info/top_level.txt
