Metadata-Version: 2.0
Name: datastore-to-gcs
Version: 0.3
Summary: Transfer data from Google Cloud Datastore to Google Cloud Storage.
Home-page: https://github.com/SocosLLC/datastore-to-gcs
Author: Brandon Istenes
Author-email: bistenes@socos.me
License: Apache License 2.0
Download-URL: https://github.com/SocosLLC/datastore-to-gcs/archive/0.3.tar.gz
Keywords: gae,gcp,gcs,gcd,datastore,cloudstorage,transfer,dump
Platform: UNKNOWN
Classifier: Development Status :: 4 - Beta
Classifier: License :: OSI Approved :: Apache Software License
Requires-Dist: GoogleAppEngineCloudStorageClient
Requires-Dist: enum
Requires-Dist: python-dateutil
Requires-Dist: toolz
